jerris_client-1.0.0.dist-info/licenses/LICENSE
jerris_jerris_client/__init__.py
jerris_jerris_client/const/__init__.py
jerris_jerris_client/const/globals.py
jerris_jerris_client/const/parameters.py
jerris_jerris_client/const/typing.py
jerris_jerris_client/errors/__init__.py
jerris_jerris_client/errors/api.py
jerris_jerris_client/helpers/__init__.py
jerris_jerris_client/helpers/image_helper.py
jerris_jerris_client/helpers/version_0_0_1.py
jerris_jerris_client/utils/__init__.py
jerris_jerris_client/utils/analyze_response.py
jerris_jerris_client/utils/jerris_client.py
jerris_client-1.0.0.dist-info/METADATA
jerris_client-1.0.0.dist-info/WHEEL
jerris_client-1.0.0.dist-info/top_level.txt
jerris_client-1.0.0.dist-info/RECORD
