Metadata-Version: 2.4
Name: jerris-client
Version: 1.0.0
Summary: Jerris API Client for Python
Author: Jerris
Author-email: contact@syrtis.be
Classifier: Programming Language :: Python :: 3
Classifier: Operating System :: OS Independent
Requires-Python: >=3.6
License-File: LICENSE
Requires-Dist: pillow
Dynamic: author
Dynamic: author-email
Dynamic: classifier
Dynamic: description
Dynamic: description-content-type
Dynamic: license-file
Dynamic: requires-dist
Dynamic: requires-python
Dynamic: summary
